mcp_blockchain/__init__.py
mcp_blockchain/__main__.py
mcp_blockchain/server.py
mcp_blockchain-0.1.1.dist-info/METADATA
mcp_blockchain-0.1.1.dist-info/WHEEL
mcp_blockchain-0.1.1.dist-info/entry_points.txt
mcp_blockchain-0.1.1.dist-info/licenses/LICENSE
mcp_blockchain-0.1.1.dist-info/RECORD
