Metadata-Version: 2.4
Name: mcp-blockchain
Version: 0.1.1
Summary: A production-grade blockchain server built using MCP (Model Context Protocol)
Author-email: Rajan Shukla <rshukla2k@gmail.com>
License-Expression: MIT
License-File: LICENSE
Keywords: blockchain,ethereum,mcp,web3
Classifier: Development Status :: 4 - Beta
Classifier: Intended Audience :: Developers
Classifier: License :: OSI Approved :: MIT License
Classifier: Programming Language :: Python :: 3
Classifier: Programming Language :: Python :: 3.10
Classifier: Programming Language :: Python :: 3.11
Classifier: Programming Language :: Python :: 3.12
Requires-Python: >=3.11
Requires-Dist: eth-utils>=2.0.0
Requires-Dist: mcp-server>=0.1.4
Requires-Dist: mcp[cli]>=1.2.0
Requires-Dist: pytest-asyncio>=0.26.0
Requires-Dist: pytest-cov>=6.1.1
Requires-Dist: pytest>=8.3.5
Requires-Dist: requests>=2.31.0
Requires-Dist: web3>=6.0.0
